{"cameraMode":{"drawMode":0,"name":"Shaded","section":"Shading Mode"},"sceneLighting":true,"audioPlay":false,"sceneViewState":{"showFog":true,"showMaterialUpdate":false,"showSkybox":true,"showFlares":true,"showImageEffects":true,"showParticleSystems":true},"in2DMode":false,"pivot":{"x":-41.008750915527347,"y":-16.729738235473634,"z":21.316171646118165},"rotation":{"x":-0.029561523348093034,"y":0.9401838779449463,"z":-0.3286791145801544,"w":-0.08456059545278549},"size":35.508548736572269,"orthographic":false}